<mxfile host="app.diagrams.net" agent="Mozilla/5.0 (X11; Linux x86_64; rv:134.0) Gecko/20100101 Firefox/134.0" version="26.0.11">
  <diagram id="diagram1" name="Database Diagram">
    <mxGraphModel dx="2048" dy="894" grid="1" gridSize="10" guides="1" tooltips="1" connect="1" arrows="1" fold="1" page="1" pageScale="1" pageWidth="827" pageHeight="1169" math="0" shadow="0">
      <root>
        <mxCell id="0" />
        <mxCell id="1" parent="0" />
        <mxCell id="WA5Wdy1DM6HMsTM9k74I-105" value="IF NOT EXISTS funcionarios" style="shape=table;startSize=30;container=1;collapsible=1;childLayout=tableLayout;fixedRows=1;rowLines=0;fontStyle=5;align=left;resizeLast=1;strokeColor=#6c8ebf;verticalAlign=middle;spacingLeft=6;fontFamily=Helvetica;fontSize=12;fillColor=#dae8fc;" vertex="1" parent="1">
          <mxGeometry x="-280" y="230" width="230" height="180" as="geometry" />
        </mxCell>
        <mxCell id="WA5Wdy1DM6HMsTM9k74I-106" value="" style="shape=tableRow;horizontal=0;startSize=0;swimlaneHead=0;swimlaneBody=0;fillColor=#ffe6cc;collapsible=0;dropTarget=0;points=[[0,0.5],[1,0.5]];portConstraint=eastwest;strokeColor=#d79b00;top=0;left=0;right=0;bottom=1;align=left;verticalAlign=middle;spacingLeft=6;fontFamily=Helvetica;fontSize=12;fontColor=default;fontStyle=5;" vertex="1" parent="WA5Wdy1DM6HMsTM9k74I-105">
          <mxGeometry y="30" width="230" height="30" as="geometry" />
        </mxCell>
        <mxCell id="WA5Wdy1DM6HMsTM9k74I-107" value="PK" style="shape=partialRectangle;overflow=hidden;connectable=0;fillColor=#ffe6cc;strokeColor=#d79b00;top=0;left=0;bottom=0;right=0;fontStyle=5;align=left;verticalAlign=middle;spacingLeft=6;fontFamily=Helvetica;fontSize=12;fontColor=default;" vertex="1" parent="WA5Wdy1DM6HMsTM9k74I-106">
          <mxGeometry width="30" height="30" as="geometry">
            <mxRectangle width="30" height="30" as="alternateBounds" />
          </mxGeometry>
        </mxCell>
        <mxCell id="WA5Wdy1DM6HMsTM9k74I-108" value="id INTEGER  AUTOINCREMENT" style="shape=partialRectangle;overflow=hidden;connectable=0;fillColor=#ffe6cc;align=left;strokeColor=#d79b00;top=0;left=0;bottom=0;right=0;spacingLeft=6;fontStyle=5;verticalAlign=middle;fontFamily=Helvetica;fontSize=12;fontColor=default;" vertex="1" parent="WA5Wdy1DM6HMsTM9k74I-106">
          <mxGeometry x="30" width="200" height="30" as="geometry">
            <mxRectangle width="200" height="30" as="alternateBounds" />
          </mxGeometry>
        </mxCell>
        <mxCell id="WA5Wdy1DM6HMsTM9k74I-109" value="" style="shape=tableRow;horizontal=0;startSize=0;swimlaneHead=0;swimlaneBody=0;fillColor=#ffe6cc;collapsible=0;dropTarget=0;points=[[0,0.5],[1,0.5]];portConstraint=eastwest;strokeColor=#d79b00;top=0;left=0;right=0;bottom=0;align=left;verticalAlign=middle;spacingLeft=6;fontFamily=Helvetica;fontSize=12;fontColor=default;fontStyle=5;" vertex="1" parent="WA5Wdy1DM6HMsTM9k74I-105">
          <mxGeometry y="60" width="230" height="30" as="geometry" />
        </mxCell>
        <mxCell id="WA5Wdy1DM6HMsTM9k74I-110" value="" style="shape=partialRectangle;overflow=hidden;connectable=0;fillColor=#ffe6cc;strokeColor=#d79b00;top=0;left=0;bottom=0;right=0;align=left;verticalAlign=middle;spacingLeft=6;fontFamily=Helvetica;fontSize=12;fontColor=default;fontStyle=5;" vertex="1" parent="WA5Wdy1DM6HMsTM9k74I-109">
          <mxGeometry width="30" height="30" as="geometry">
            <mxRectangle width="30" height="30" as="alternateBounds" />
          </mxGeometry>
        </mxCell>
        <mxCell id="WA5Wdy1DM6HMsTM9k74I-111" value="username TEXT UNIQUE" style="shape=partialRectangle;overflow=hidden;connectable=0;fillColor=#ffe6cc;align=left;strokeColor=#d79b00;top=0;left=0;bottom=0;right=0;spacingLeft=6;verticalAlign=middle;fontFamily=Helvetica;fontSize=12;fontColor=default;fontStyle=5;" vertex="1" parent="WA5Wdy1DM6HMsTM9k74I-109">
          <mxGeometry x="30" width="200" height="30" as="geometry">
            <mxRectangle width="200" height="30" as="alternateBounds" />
          </mxGeometry>
        </mxCell>
        <mxCell id="WA5Wdy1DM6HMsTM9k74I-112" value="" style="shape=tableRow;horizontal=0;startSize=0;swimlaneHead=0;swimlaneBody=0;fillColor=#ffe6cc;collapsible=0;dropTarget=0;points=[[0,0.5],[1,0.5]];portConstraint=eastwest;strokeColor=#d79b00;top=0;left=0;right=0;bottom=0;align=left;verticalAlign=middle;spacingLeft=6;fontFamily=Helvetica;fontSize=12;fontColor=default;fontStyle=5;" vertex="1" parent="WA5Wdy1DM6HMsTM9k74I-105">
          <mxGeometry y="90" width="230" height="30" as="geometry" />
        </mxCell>
        <mxCell id="WA5Wdy1DM6HMsTM9k74I-113" value="" style="shape=partialRectangle;overflow=hidden;connectable=0;fillColor=#ffe6cc;strokeColor=#d79b00;top=0;left=0;bottom=0;right=0;align=left;verticalAlign=middle;spacingLeft=6;fontFamily=Helvetica;fontSize=12;fontColor=default;fontStyle=5;" vertex="1" parent="WA5Wdy1DM6HMsTM9k74I-112">
          <mxGeometry width="30" height="30" as="geometry">
            <mxRectangle width="30" height="30" as="alternateBounds" />
          </mxGeometry>
        </mxCell>
        <mxCell id="WA5Wdy1DM6HMsTM9k74I-114" value="password TEXT" style="shape=partialRectangle;overflow=hidden;connectable=0;fillColor=#ffe6cc;align=left;strokeColor=#d79b00;top=0;left=0;bottom=0;right=0;spacingLeft=6;verticalAlign=middle;fontFamily=Helvetica;fontSize=12;fontColor=default;fontStyle=5;" vertex="1" parent="WA5Wdy1DM6HMsTM9k74I-112">
          <mxGeometry x="30" width="200" height="30" as="geometry">
            <mxRectangle width="200" height="30" as="alternateBounds" />
          </mxGeometry>
        </mxCell>
        <mxCell id="WA5Wdy1DM6HMsTM9k74I-115" value="" style="shape=tableRow;horizontal=0;startSize=0;swimlaneHead=0;swimlaneBody=0;fillColor=#ffe6cc;collapsible=0;dropTarget=0;points=[[0,0.5],[1,0.5]];portConstraint=eastwest;strokeColor=#d79b00;top=0;left=0;right=0;bottom=0;align=left;verticalAlign=middle;spacingLeft=6;fontFamily=Helvetica;fontSize=12;fontColor=default;fontStyle=5;" vertex="1" parent="WA5Wdy1DM6HMsTM9k74I-105">
          <mxGeometry y="120" width="230" height="30" as="geometry" />
        </mxCell>
        <mxCell id="WA5Wdy1DM6HMsTM9k74I-116" value="" style="shape=partialRectangle;overflow=hidden;connectable=0;fillColor=#ffe6cc;strokeColor=#d79b00;top=0;left=0;bottom=0;right=0;align=left;verticalAlign=middle;spacingLeft=6;fontFamily=Helvetica;fontSize=12;fontColor=default;fontStyle=5;" vertex="1" parent="WA5Wdy1DM6HMsTM9k74I-115">
          <mxGeometry width="30" height="30" as="geometry">
            <mxRectangle width="30" height="30" as="alternateBounds" />
          </mxGeometry>
        </mxCell>
        <mxCell id="WA5Wdy1DM6HMsTM9k74I-117" value="nome TEXT" style="shape=partialRectangle;overflow=hidden;connectable=0;fillColor=#ffe6cc;align=left;strokeColor=#d79b00;top=0;left=0;bottom=0;right=0;spacingLeft=6;strokeWidth=2;verticalAlign=middle;fontFamily=Helvetica;fontSize=12;fontColor=default;fontStyle=5;" vertex="1" parent="WA5Wdy1DM6HMsTM9k74I-115">
          <mxGeometry x="30" width="200" height="30" as="geometry">
            <mxRectangle width="200" height="30" as="alternateBounds" />
          </mxGeometry>
        </mxCell>
        <mxCell id="WA5Wdy1DM6HMsTM9k74I-118" value="" style="shape=tableRow;horizontal=0;startSize=0;swimlaneHead=0;swimlaneBody=0;fillColor=#ffe6cc;collapsible=0;dropTarget=0;points=[[0,0.5],[1,0.5]];portConstraint=eastwest;strokeColor=#d79b00;top=0;left=0;right=0;bottom=0;align=left;verticalAlign=middle;spacingLeft=6;fontFamily=Helvetica;fontSize=12;fontColor=default;fontStyle=5;" vertex="1" parent="WA5Wdy1DM6HMsTM9k74I-105">
          <mxGeometry y="150" width="230" height="30" as="geometry" />
        </mxCell>
        <mxCell id="WA5Wdy1DM6HMsTM9k74I-119" value="" style="shape=partialRectangle;overflow=hidden;connectable=0;fillColor=#ffe6cc;strokeColor=#d79b00;top=0;left=0;bottom=0;right=0;align=left;verticalAlign=middle;spacingLeft=6;fontFamily=Helvetica;fontSize=12;fontColor=default;fontStyle=5;" vertex="1" parent="WA5Wdy1DM6HMsTM9k74I-118">
          <mxGeometry width="30" height="30" as="geometry">
            <mxRectangle width="30" height="30" as="alternateBounds" />
          </mxGeometry>
        </mxCell>
        <mxCell id="WA5Wdy1DM6HMsTM9k74I-120" value="role INTEGER DEFAULT 1" style="shape=partialRectangle;overflow=hidden;connectable=0;fillColor=#ffe6cc;align=left;strokeColor=#d79b00;top=0;left=0;bottom=0;right=0;spacingLeft=6;strokeWidth=2;verticalAlign=middle;fontFamily=Helvetica;fontSize=12;fontColor=default;fontStyle=5;" vertex="1" parent="WA5Wdy1DM6HMsTM9k74I-118">
          <mxGeometry x="30" width="200" height="30" as="geometry">
            <mxRectangle width="200" height="30" as="alternateBounds" />
          </mxGeometry>
        </mxCell>
        <mxCell id="WA5Wdy1DM6HMsTM9k74I-121" value="IF NOT EXISTS alergias_funcionarios" style="shape=table;startSize=30;container=1;collapsible=1;childLayout=tableLayout;fixedRows=1;rowLines=0;fontStyle=1;align=center;resizeLast=1;fillColor=#dae8fc;strokeColor=#6c8ebf;" vertex="1" parent="1">
          <mxGeometry x="70" y="170" width="230" height="120" as="geometry">
            <mxRectangle x="70" y="170" width="240" height="30" as="alternateBounds" />
          </mxGeometry>
        </mxCell>
        <mxCell id="WA5Wdy1DM6HMsTM9k74I-122" value="" style="shape=tableRow;horizontal=0;startSize=0;swimlaneHead=0;swimlaneBody=0;fillColor=none;collapsible=0;dropTarget=0;points=[[0,0.5],[1,0.5]];portConstraint=eastwest;strokeColor=inherit;top=0;left=0;right=0;bottom=1;" vertex="1" parent="WA5Wdy1DM6HMsTM9k74I-121">
          <mxGeometry y="30" width="230" height="30" as="geometry" />
        </mxCell>
        <mxCell id="WA5Wdy1DM6HMsTM9k74I-123" value="PK" style="shape=partialRectangle;overflow=hidden;connectable=0;fillColor=#ffe6cc;strokeColor=#d79b00;top=0;left=0;bottom=0;right=0;fontStyle=5;" vertex="1" parent="WA5Wdy1DM6HMsTM9k74I-122">
          <mxGeometry width="30" height="30" as="geometry">
            <mxRectangle width="30" height="30" as="alternateBounds" />
          </mxGeometry>
        </mxCell>
        <mxCell id="WA5Wdy1DM6HMsTM9k74I-124" value="id INTEGER  AUTOINCREMENT" style="shape=partialRectangle;overflow=hidden;connectable=0;fillColor=#ffe6cc;align=left;strokeColor=#d79b00;top=0;left=0;bottom=0;right=0;spacingLeft=6;fontStyle=5;" vertex="1" parent="WA5Wdy1DM6HMsTM9k74I-122">
          <mxGeometry x="30" width="200" height="30" as="geometry">
            <mxRectangle width="200" height="30" as="alternateBounds" />
          </mxGeometry>
        </mxCell>
        <mxCell id="WA5Wdy1DM6HMsTM9k74I-125" value="" style="shape=tableRow;horizontal=0;startSize=0;swimlaneHead=0;swimlaneBody=0;fillColor=#ffe6cc;collapsible=0;dropTarget=0;points=[[0,0.5],[1,0.5]];portConstraint=eastwest;strokeColor=#d79b00;top=0;left=0;right=0;bottom=0;" vertex="1" parent="WA5Wdy1DM6HMsTM9k74I-121">
          <mxGeometry y="60" width="230" height="30" as="geometry" />
        </mxCell>
        <mxCell id="WA5Wdy1DM6HMsTM9k74I-126" value="FK" style="shape=partialRectangle;overflow=hidden;connectable=0;fillColor=#ffe6cc;strokeColor=#d79b00;top=0;left=0;bottom=0;right=0;fontStyle=5" vertex="1" parent="WA5Wdy1DM6HMsTM9k74I-125">
          <mxGeometry width="30" height="30" as="geometry">
            <mxRectangle width="30" height="30" as="alternateBounds" />
          </mxGeometry>
        </mxCell>
        <mxCell id="WA5Wdy1DM6HMsTM9k74I-127" value="funcionario_id INTEGER" style="shape=partialRectangle;overflow=hidden;connectable=0;fillColor=#ffe6cc;align=left;strokeColor=#d79b00;top=0;left=0;bottom=0;right=0;spacingLeft=6;fontStyle=5" vertex="1" parent="WA5Wdy1DM6HMsTM9k74I-125">
          <mxGeometry x="30" width="200" height="30" as="geometry">
            <mxRectangle width="200" height="30" as="alternateBounds" />
          </mxGeometry>
        </mxCell>
        <mxCell id="WA5Wdy1DM6HMsTM9k74I-128" value="" style="shape=tableRow;horizontal=0;startSize=0;swimlaneHead=0;swimlaneBody=0;fillColor=#ffe6cc;collapsible=0;dropTarget=0;points=[[0,0.5],[1,0.5]];portConstraint=eastwest;strokeColor=#d79b00;top=0;left=0;right=0;bottom=0;" vertex="1" parent="WA5Wdy1DM6HMsTM9k74I-121">
          <mxGeometry y="90" width="230" height="30" as="geometry" />
        </mxCell>
        <mxCell id="WA5Wdy1DM6HMsTM9k74I-129" value="" style="shape=partialRectangle;overflow=hidden;connectable=0;fillColor=#ffe6cc;strokeColor=#d79b00;top=0;left=0;bottom=0;right=0;" vertex="1" parent="WA5Wdy1DM6HMsTM9k74I-128">
          <mxGeometry width="30" height="30" as="geometry">
            <mxRectangle width="30" height="30" as="alternateBounds" />
          </mxGeometry>
        </mxCell>
        <mxCell id="WA5Wdy1DM6HMsTM9k74I-130" value="alergias TEXT" style="shape=partialRectangle;overflow=hidden;connectable=0;fillColor=#ffe6cc;align=left;strokeColor=#d79b00;top=0;left=0;bottom=0;right=0;spacingLeft=6;fontStyle=5" vertex="1" parent="WA5Wdy1DM6HMsTM9k74I-128">
          <mxGeometry x="30" width="200" height="30" as="geometry">
            <mxRectangle width="200" height="30" as="alternateBounds" />
          </mxGeometry>
        </mxCell>
        <mxCell id="WA5Wdy1DM6HMsTM9k74I-131" value="IF NOT EXISTS presencas" style="shape=table;startSize=30;container=1;collapsible=1;childLayout=tableLayout;fixedRows=1;rowLines=0;fontStyle=5;align=left;resizeLast=1;fillColor=#dae8fc;strokeColor=#6c8ebf;strokeWidth=1;verticalAlign=middle;spacingLeft=6;fontFamily=Helvetica;fontSize=12;" vertex="1" parent="1">
          <mxGeometry x="70" y="360" width="250" height="180" as="geometry" />
        </mxCell>
        <mxCell id="WA5Wdy1DM6HMsTM9k74I-132" value="" style="shape=tableRow;horizontal=0;startSize=0;swimlaneHead=0;swimlaneBody=0;fillColor=#ffe6cc;collapsible=0;dropTarget=0;points=[[0,0.5],[1,0.5]];portConstraint=eastwest;strokeColor=#d79b00;top=0;left=0;right=0;bottom=1;strokeWidth=2;align=left;verticalAlign=middle;spacingLeft=6;fontFamily=Helvetica;fontSize=12;fontColor=default;fontStyle=5;" vertex="1" parent="WA5Wdy1DM6HMsTM9k74I-131">
          <mxGeometry y="30" width="250" height="30" as="geometry" />
        </mxCell>
        <mxCell id="WA5Wdy1DM6HMsTM9k74I-133" value="PK" style="shape=partialRectangle;overflow=hidden;connectable=0;fillColor=#ffe6cc;strokeColor=#d79b00;top=0;left=0;bottom=0;right=0;fontStyle=5;strokeWidth=2;align=left;verticalAlign=middle;spacingLeft=6;fontFamily=Helvetica;fontSize=12;fontColor=default;" vertex="1" parent="WA5Wdy1DM6HMsTM9k74I-132">
          <mxGeometry width="30" height="30" as="geometry">
            <mxRectangle width="30" height="30" as="alternateBounds" />
          </mxGeometry>
        </mxCell>
        <mxCell id="WA5Wdy1DM6HMsTM9k74I-134" value="id INTEGER  AUTOINCREMENT" style="shape=partialRectangle;overflow=hidden;connectable=0;fillColor=#ffe6cc;align=left;strokeColor=#d79b00;top=0;left=0;bottom=0;right=0;spacingLeft=6;fontStyle=5;strokeWidth=2;verticalAlign=middle;fontFamily=Helvetica;fontSize=12;fontColor=default;" vertex="1" parent="WA5Wdy1DM6HMsTM9k74I-132">
          <mxGeometry x="30" width="220" height="30" as="geometry">
            <mxRectangle width="220" height="30" as="alternateBounds" />
          </mxGeometry>
        </mxCell>
        <mxCell id="WA5Wdy1DM6HMsTM9k74I-135" value="" style="shape=tableRow;horizontal=0;startSize=0;swimlaneHead=0;swimlaneBody=0;fillColor=#ffe6cc;collapsible=0;dropTarget=0;points=[[0,0.5],[1,0.5]];portConstraint=eastwest;strokeColor=#d79b00;top=0;left=0;right=0;bottom=0;strokeWidth=2;align=left;verticalAlign=middle;spacingLeft=6;fontFamily=Helvetica;fontSize=12;fontColor=default;fontStyle=5;" vertex="1" parent="WA5Wdy1DM6HMsTM9k74I-131">
          <mxGeometry y="60" width="250" height="30" as="geometry" />
        </mxCell>
        <mxCell id="WA5Wdy1DM6HMsTM9k74I-136" value="FK" style="shape=partialRectangle;overflow=hidden;connectable=0;fillColor=#ffe6cc;strokeColor=#d79b00;top=0;left=0;bottom=0;right=0;fontStyle=5;strokeWidth=2;align=left;verticalAlign=middle;spacingLeft=6;fontFamily=Helvetica;fontSize=12;fontColor=default;" vertex="1" parent="WA5Wdy1DM6HMsTM9k74I-135">
          <mxGeometry width="30" height="30" as="geometry">
            <mxRectangle width="30" height="30" as="alternateBounds" />
          </mxGeometry>
        </mxCell>
        <mxCell id="WA5Wdy1DM6HMsTM9k74I-137" value="funcionario_id INTEGER" style="shape=partialRectangle;overflow=hidden;connectable=0;fillColor=#ffe6cc;align=left;strokeColor=#d79b00;top=0;left=0;bottom=0;right=0;spacingLeft=6;strokeWidth=2;verticalAlign=middle;fontFamily=Helvetica;fontSize=12;fontColor=default;fontStyle=5;" vertex="1" parent="WA5Wdy1DM6HMsTM9k74I-135">
          <mxGeometry x="30" width="220" height="30" as="geometry">
            <mxRectangle width="220" height="30" as="alternateBounds" />
          </mxGeometry>
        </mxCell>
        <mxCell id="WA5Wdy1DM6HMsTM9k74I-138" value="" style="shape=tableRow;horizontal=0;startSize=0;swimlaneHead=0;swimlaneBody=0;fillColor=#ffe6cc;collapsible=0;dropTarget=0;points=[[0,0.5],[1,0.5]];portConstraint=eastwest;strokeColor=#d79b00;top=0;left=0;right=0;bottom=0;strokeWidth=2;align=left;verticalAlign=middle;spacingLeft=6;fontFamily=Helvetica;fontSize=12;fontColor=default;fontStyle=5;" vertex="1" parent="WA5Wdy1DM6HMsTM9k74I-131">
          <mxGeometry y="90" width="250" height="30" as="geometry" />
        </mxCell>
        <mxCell id="WA5Wdy1DM6HMsTM9k74I-139" value="" style="shape=partialRectangle;overflow=hidden;connectable=0;fillColor=#ffe6cc;strokeColor=#d79b00;top=0;left=0;bottom=0;right=0;strokeWidth=2;align=left;verticalAlign=middle;spacingLeft=6;fontFamily=Helvetica;fontSize=12;fontColor=default;fontStyle=5;" vertex="1" parent="WA5Wdy1DM6HMsTM9k74I-138">
          <mxGeometry width="30" height="30" as="geometry">
            <mxRectangle width="30" height="30" as="alternateBounds" />
          </mxGeometry>
        </mxCell>
        <mxCell id="WA5Wdy1DM6HMsTM9k74I-140" value="presenca BOOLEAN" style="shape=partialRectangle;overflow=hidden;connectable=0;fillColor=#ffe6cc;align=left;strokeColor=#d79b00;top=0;left=0;bottom=0;right=0;spacingLeft=6;strokeWidth=2;verticalAlign=middle;fontFamily=Helvetica;fontSize=12;fontColor=default;fontStyle=5;" vertex="1" parent="WA5Wdy1DM6HMsTM9k74I-138">
          <mxGeometry x="30" width="220" height="30" as="geometry">
            <mxRectangle width="220" height="30" as="alternateBounds" />
          </mxGeometry>
        </mxCell>
        <mxCell id="WA5Wdy1DM6HMsTM9k74I-141" value="" style="shape=tableRow;horizontal=0;startSize=0;swimlaneHead=0;swimlaneBody=0;fillColor=#ffe6cc;collapsible=0;dropTarget=0;points=[[0,0.5],[1,0.5]];portConstraint=eastwest;strokeColor=#d79b00;top=0;left=0;right=0;bottom=0;strokeWidth=2;align=left;verticalAlign=middle;spacingLeft=6;fontFamily=Helvetica;fontSize=12;fontColor=default;fontStyle=5;" vertex="1" parent="WA5Wdy1DM6HMsTM9k74I-131">
          <mxGeometry y="120" width="250" height="30" as="geometry" />
        </mxCell>
        <mxCell id="WA5Wdy1DM6HMsTM9k74I-142" value="" style="shape=partialRectangle;overflow=hidden;connectable=0;fillColor=#ffe6cc;strokeColor=#d79b00;top=0;left=0;bottom=0;right=0;strokeWidth=2;align=left;verticalAlign=middle;spacingLeft=6;fontFamily=Helvetica;fontSize=12;fontColor=default;fontStyle=5;" vertex="1" parent="WA5Wdy1DM6HMsTM9k74I-141">
          <mxGeometry width="30" height="30" as="geometry">
            <mxRectangle width="30" height="30" as="alternateBounds" />
          </mxGeometry>
        </mxCell>
        <mxCell id="WA5Wdy1DM6HMsTM9k74I-143" value="data TEXT DEFAULT (DATE(&#39;now&#39;))" style="shape=partialRectangle;overflow=hidden;connectable=0;fillColor=#ffe6cc;align=left;strokeColor=#d79b00;top=0;left=0;bottom=0;right=0;spacingLeft=6;strokeWidth=2;verticalAlign=middle;fontFamily=Helvetica;fontSize=12;fontColor=default;fontStyle=5;" vertex="1" parent="WA5Wdy1DM6HMsTM9k74I-141">
          <mxGeometry x="30" width="220" height="30" as="geometry">
            <mxRectangle width="220" height="30" as="alternateBounds" />
          </mxGeometry>
        </mxCell>
        <mxCell id="WA5Wdy1DM6HMsTM9k74I-144" style="edgeStyle=orthogonalEdgeStyle;rounded=0;orthogonalLoop=1;jettySize=auto;html=1;exitX=0;exitY=0.5;exitDx=0;exitDy=0;entryX=1;entryY=0.5;entryDx=0;entryDy=0;" edge="1" parent="1" source="WA5Wdy1DM6HMsTM9k74I-125" target="WA5Wdy1DM6HMsTM9k74I-106">
          <mxGeometry relative="1" as="geometry" />
        </mxCell>
        <mxCell id="WA5Wdy1DM6HMsTM9k74I-145" style="edgeStyle=orthogonalEdgeStyle;rounded=0;orthogonalLoop=1;jettySize=auto;html=1;exitX=0;exitY=0.5;exitDx=0;exitDy=0;entryX=0.987;entryY=0.783;entryDx=0;entryDy=0;entryPerimeter=0;" edge="1" parent="1" source="WA5Wdy1DM6HMsTM9k74I-135" target="WA5Wdy1DM6HMsTM9k74I-106">
          <mxGeometry relative="1" as="geometry" />
        </mxCell>
        <mxCell id="WA5Wdy1DM6HMsTM9k74I-146" value="funcionario_id, data" style="shape=partialRectangle;overflow=hidden;connectable=0;fillColor=#ffe6cc;align=left;strokeColor=#d79b00;top=0;left=0;bottom=0;right=0;spacingLeft=6;strokeWidth=2;verticalAlign=middle;fontFamily=Helvetica;fontSize=12;fontColor=default;fontStyle=5;" vertex="1" parent="1">
          <mxGeometry x="100" y="510" width="220" height="30" as="geometry">
            <mxRectangle width="220" height="30" as="alternateBounds" />
          </mxGeometry>
        </mxCell>
        <mxCell id="WA5Wdy1DM6HMsTM9k74I-147" value="UN" style="shape=partialRectangle;overflow=hidden;connectable=0;fillColor=#ffe6cc;strokeColor=#d79b00;top=0;left=0;bottom=0;right=0;strokeWidth=2;align=left;verticalAlign=middle;spacingLeft=6;fontFamily=Helvetica;fontSize=12;fontColor=default;fontStyle=5;" vertex="1" parent="1">
          <mxGeometry x="70" y="510" width="30" height="30" as="geometry">
            <mxRectangle width="30" height="30" as="alternateBounds" />
          </mxGeometry>
        </mxCell>
      </root>
    </mxGraphModel>
  </diagram>
</mxfile>
